odoo/addons/sale_multi_template_application/README.rst
odoo/addons/sale_multi_template_application/__init__.py
odoo/addons/sale_multi_template_application/__manifest__.py
odoo/addons/sale_multi_template_application/i18n/it.po
odoo/addons/sale_multi_template_application/i18n/sale_multi_template_application.pot
odoo/addons/sale_multi_template_application/models/__init__.py
odoo/addons/sale_multi_template_application/models/sale_order.py
odoo/addons/sale_multi_template_application/readme/CONFIGURE.md
odoo/addons/sale_multi_template_application/readme/CONTRIBUTORS.md
odoo/addons/sale_multi_template_application/readme/DESCRIPTION.md
odoo/addons/sale_multi_template_application/readme/USAGE.md
odoo/addons/sale_multi_template_application/static/description/icon.png
odoo/addons/sale_multi_template_application/static/description/index.html
odoo/addons/sale_multi_template_application/tests/__init__.py
odoo/addons/sale_multi_template_application/tests/test_sale_multi_template_application.py
odoo_addon_sale_multi_template_application-17.0.1.0.0.4.dist-info/METADATA
odoo_addon_sale_multi_template_application-17.0.1.0.0.4.dist-info/WHEEL
odoo_addon_sale_multi_template_application-17.0.1.0.0.4.dist-info/top_level.txt
odoo_addon_sale_multi_template_application-17.0.1.0.0.4.dist-info/RECORD
